dvc_task/__init__.py
dvc_task/exceptions.py
dvc_task/py.typed
dvc_task/utils.py
dvc_task/app/__init__.py
dvc_task/app/filesystem.py
dvc_task/proc/__init__.py
dvc_task/proc/exceptions.py
dvc_task/proc/manager.py
dvc_task/proc/process.py
dvc_task/proc/tasks.py
dvc_task/worker/__init__.py
dvc_task/worker/temporary.py
dvc_task-0.40.2.dist-info/LICENSE
dvc_task-0.40.2.dist-info/METADATA
dvc_task-0.40.2.dist-info/WHEEL
dvc_task-0.40.2.dist-info/top_level.txt
dvc_task-0.40.2.dist-info/RECORD
