Metadata-Version: 2.1
Name: dvc-task
Version: 0.40.2
Summary: Extensible task queue used in DVC.
Author-email: Iterative <support@dvc.org>
License: Apache-2.0
Project-URL: Issues, https://github.com/iterative/dvc-task/issues
Project-URL: Source, https://github.com/iterative/dvc-task
Classifier: Programming Language :: Python :: 3
Classifier: Programming Language :: Python :: 3.8
Classifier: Programming Language :: Python :: 3.9
Classifier: Programming Language :: Python :: 3.10
Classifier: Programming Language :: Python :: 3.11
Classifier: Programming Language :: Python :: 3.12
Classifier: Programming Language :: Python :: 3.13
Classifier: Development Status :: 4 - Beta
Requires-Python: >=3.8
License-File: LICENSE
Requires-Dist: celery<6,>=5.3.0
Requires-Dist: funcy>=1.17
Requires-Dist: kombu<6,>=5.3.0
Requires-Dist: pywin32>=225; sys_platform == "win32"
Requires-Dist: shortuuid>=1.0.8
Provides-Extra: docs
Requires-Dist: mkdocs<2,>=1.5.2; extra == "docs"
Requires-Dist: mkdocs-gen-files<1,>=0.5.0; extra == "docs"
Requires-Dist: mkdocs-material<10,>=9.3.1; extra == "docs"
Requires-Dist: mkdocs-section-index<1,>=0.3.6; extra == "docs"
Requires-Dist: mkdocstrings-python<2,>=1.6.3; extra == "docs"
Provides-Extra: tests
Requires-Dist: pytest<9,>=7; extra == "tests"
Requires-Dist: pytest-celery<1; extra == "tests"
Requires-Dist: pytest-cov>=4.1.0; extra == "tests"
Requires-Dist: pytest-mock; extra == "tests"
Requires-Dist: pytest-rerunfailures; extra == "tests"
Requires-Dist: pytest-sugar; extra == "tests"
Requires-Dist: pytest-test-utils>=0.0.6; extra == "tests"
Provides-Extra: dev
Requires-Dist: dvc-task[docs,tests]; extra == "dev"
Requires-Dist: celery-types; python_version > "3.9" and extra == "dev"
Requires-Dist: celery-types==0.15.0; python_version < "3.9" and extra == "dev"
Requires-Dist: mypy==1.11.2; extra == "dev"
